MANIFEST.in
README.md
requirements_dev.txt
requirements_extra.txt
setup.cfg
setup.py
version.py
gitmodules_mercurio.egg-info/PKG-INFO
gitmodules_mercurio.egg-info/SOURCES.txt
gitmodules_mercurio.egg-info/dependency_links.txt
gitmodules_mercurio.egg-info/not-zip-safe
gitmodules_mercurio.egg-info/requires.txt
gitmodules_mercurio.egg-info/top_level.txt
module_A/__init__.py
module_A/setup.py
module_A/version_module_A.py
module_B/__init__.py
module_B/setup.py
module_B/version_module_B.py